py_solace_provision-0.2.9.data/scripts/pysolpro.py
sp/ArgParseCache.py
sp/AutoApi.py
sp/CallProxy.py
sp/DataPersist.py
sp/SettingsLoader.py
sp/SolaceResponseProcessor.py
sp/SubCommandConfig.py
sp/__init__.py
sp/nw.py
sp/util.py
py_solace_provision-0.2.9.dist-info/METADATA
py_solace_provision-0.2.9.dist-info/WHEEL
py_solace_provision-0.2.9.dist-info/top_level.txt
py_solace_provision-0.2.9.dist-info/RECORD
