Metadata-Version: 2.1
Name: py-solace-provision
Version: 0.2.9
Summary: A solace provisioning toolkit
Home-page: https://github.com/unixunion/py-solace-provision
Author: Kegan Holtzhausen
Author-email: marzubus@gmail.com
License: BSD
Keywords: solace messaging provioning
Platform: UNKNOWN
Classifier: Development Status :: 5 - Production/Stable
Classifier: Topic :: Utilities
Classifier: License :: OSI Approved :: BSD License
Requires-Dist: libkplug
Requires-Dist: six
Requires-Dist: pyyaml
